recitations_segmenter/__init__.py
recitations_segmenter/cli.py
recitations_segmenter/segment.py
recitations_segmenter/utils.py
recitations_segmenter/train/__init__.py
recitations_segmenter/train/augment.py
recitations_segmenter/train/process_data.py
recitations_segmenter/train/vad_utils.py
recitations_segmenter-1.0.0.dist-info/licenses/LICENSE
recitations_segmenter-1.0.0.dist-info/METADATA
recitations_segmenter-1.0.0.dist-info/WHEEL
recitations_segmenter-1.0.0.dist-info/entry_points.txt
recitations_segmenter-1.0.0.dist-info/top_level.txt
recitations_segmenter-1.0.0.dist-info/RECORD
