Metadata-Version: 2.4
Name: recitations-segmenter
Version: 1.0.0
Summary: Split The Holy Quran Recitations based on وفق (pause)
Author-email: Abdullah <abdullahamlyossef@gmail.com>
License-Expression: MIT
Project-URL: Homepage, https://github.com/obadx/recitations-segmenter
Project-URL: Issues, https://github.com/obadx/recitations-segmenter/issues
Classifier: Programming Language :: Python :: 3.10
Classifier: Programming Language :: Python :: 3.11
Classifier: Programming Language :: Python :: 3.12
Classifier: Programming Language :: Python :: 3.13
Classifier: Operating System :: OS Independent
Requires-Python: >=3.10
License-File: LICENSE
Requires-Dist: torch>=2.6.0
Requires-Dist: numpy
Requires-Dist: torchaudio
Requires-Dist: transformers>=4.50.3
Provides-Extra: test
Requires-Dist: pytest; extra == "test"
Provides-Extra: augment
Requires-Dist: pypdl==1.4.4; extra == "augment"
Requires-Dist: filetype==1.2.0; extra == "augment"
Requires-Dist: mutagen==1.47.0; extra == "augment"
Requires-Dist: torch==2.6.0; extra == "augment"
Requires-Dist: numpy; extra == "augment"
Requires-Dist: torchaudio; extra == "augment"
Requires-Dist: pyyaml; extra == "augment"
Requires-Dist: librosa==0.10.2; extra == "augment"
Requires-Dist: standard-aifc; extra == "augment"
Requires-Dist: standard-sunau; extra == "augment"
Requires-Dist: submitit==1.5.2; extra == "augment"
Requires-Dist: transformers==4.50.3; extra == "augment"
Requires-Dist: pyaml; extra == "augment"
Requires-Dist: pydantic==2.11.3; extra == "augment"
Requires-Dist: datasets==3.3.2; extra == "augment"
Requires-Dist: huggingface_hub; extra == "augment"
Requires-Dist: audiomentations==0.40.0; extra == "augment"
Requires-Dist: pydub<1,>=0.22.0; extra == "augment"
Requires-Dist: pyroomacoustics>=0.7.4; extra == "augment"
Requires-Dist: pytest==8.3.5; extra == "augment"
Provides-Extra: train
Requires-Dist: datasets==3.3.2; extra == "train"
Requires-Dist: huggingface_hub; extra == "train"
Requires-Dist: pytest==8.3.5; extra == "train"
Requires-Dist: scikit-learn; extra == "train"
Requires-Dist: accelerate==1.6.0; extra == "train"
Requires-Dist: tensorboard==2.19.0; extra == "train"
Dynamic: license-file
